module_swap/__init__.py
module_swap/forms.py
module_swap/models.py
module_swap/navigation.py
module_swap/urls.py
module_swap/views.py
module_swap/migrations/0001_initial.py
module_swap/migrations/__init__.py
module_swap/templates/module_swap/link_module_inventory.html
module_swap/templates/module_swap/link_module_inventory_confirm_delete.html
module_swap/templates/module_swap/link_module_inventory_list.html
module_swap/templates/module_swap/step1_select.html
module_swap/templates/module_swap/step2_bay.html
module_swap-1.2.1.dist-info/licenses/LICENSE
module_swap-1.2.1.dist-info/METADATA
module_swap-1.2.1.dist-info/WHEEL
module_swap-1.2.1.dist-info/top_level.txt
module_swap-1.2.1.dist-info/RECORD
